buca.py
buca-0.0.2.dist-info/LICENSE
buca-0.0.2.dist-info/METADATA
buca-0.0.2.dist-info/WHEEL
buca-0.0.2.dist-info/entry_points.txt
buca-0.0.2.dist-info/top_level.txt
buca-0.0.2.dist-info/RECORD
