Metadata-Version: 2.1
Name: buca
Version: 0.0.2
Summary: Blank random words in a text
Home-page: https://github.com/bfontaine/buca
Author: Baptiste Fontaine
Author-email: b@ptistefontaine.fr
License: MIT License
Platform: UNKNOWN
Classifier: Environment :: Console
Classifier: License :: OSI Approved :: MIT License
Classifier: Programming Language :: Python :: 3.6
Classifier: Programming Language :: Python :: 3.7
